ontolopy/__init__.py
ontolopy/obo.py
ontolopy/relations.py
ontolopy/uberon.py
ontolopy/version.py
ontolopy-1.1.1b0.dist-info/LICENSE.md
ontolopy-1.1.1b0.dist-info/METADATA
ontolopy-1.1.1b0.dist-info/WHEEL
ontolopy-1.1.1b0.dist-info/top_level.txt
ontolopy-1.1.1b0.dist-info/RECORD
