Metadata-Version: 2.1
Name: ontolopy
Version: 1.1.1b0
Summary: Ontolopy is a package for working with ontology (.obo) files from Python.
Home-page: https://github.com/NatalieThurlby/ontolopy
Author: Natalie Thurlby
Author-email: natalie.thurlby@bristol.ac.uk
License: MIT
Platform: UNKNOWN
Classifier: Programming Language :: Python :: 3
Requires-Python: >=3.6
Requires-Dist: pandas
Requires-Dist: numpy
Requires-Dist: validators
